rocm_llvm_python/__init__.py
rocm_llvm_python-0.0.2.dist-info/METADATA
rocm_llvm_python-0.0.2.dist-info/WHEEL
rocm_llvm_python-0.0.2.dist-info/top_level.txt
rocm_llvm_python-0.0.2.dist-info/RECORD
